protoprimer
repo_support
test_support
