Metadata-Version: 2.4
Name: protoprimer
Version: 0.0.1
Summary: universal multi-stage `python` environment initializer & bootstrapper (primer) via a stand-alone automatic (proto) script
Author: uvsmtid
Author-email: uvsmtid@gmail.com
License: MIT
Keywords: boot env bootstrap environment dev
Classifier: Development Status :: 3 - Alpha
Classifier: Environment :: Console
Classifier: Intended Audience :: Information Technology
Classifier: Topic :: Terminals
Classifier: Topic :: System :: Shells
Classifier: Programming Language :: Python :: 3
Classifier: Operating System :: POSIX :: Linux
Requires-Python: >=3.8
Provides-Extra: repo
Provides-Extra: test
Requires-Dist: pyfakefs; extra == "test"
Dynamic: author
Dynamic: author-email
Dynamic: classifier
Dynamic: description
Dynamic: keywords
Dynamic: license
Dynamic: provides-extra
Dynamic: requires-python
Dynamic: summary
